bbclib/__init__.py
bbclib/compat/__init__.py
bbclib/compat/bbclib.py
bbclib/libs/__init__.py
bbclib/libs/bbclib_asset.py
bbclib/libs/bbclib_asset_hash.py
bbclib/libs/bbclib_asset_raw.py
bbclib/libs/bbclib_binary.py
bbclib/libs/bbclib_config.py
bbclib/libs/bbclib_crossref.py
bbclib/libs/bbclib_error.py
bbclib/libs/bbclib_event.py
bbclib/libs/bbclib_keypair.py
bbclib/libs/bbclib_keypair_fast.py
bbclib/libs/bbclib_msgtype.py
bbclib/libs/bbclib_pointer.py
bbclib/libs/bbclib_reference.py
bbclib/libs/bbclib_relation.py
bbclib/libs/bbclib_signature.py
bbclib/libs/bbclib_transaction.py
bbclib/libs/bbclib_utils.py
bbclib/libs/bbclib_wire.py
bbclib/libs/bbclib_witness.py
py_bbclib-1.6.1.data/scripts/copy_libbbcsig
py_bbclib-1.6.1.data/scripts/install_libbbcsig
py_bbclib-1.6.1.dist-info/AUTHORS
py_bbclib-1.6.1.dist-info/LICENSE
py_bbclib-1.6.1.dist-info/METADATA
py_bbclib-1.6.1.dist-info/WHEEL
py_bbclib-1.6.1.dist-info/top_level.txt
py_bbclib-1.6.1.dist-info/RECORD
