Metadata-Version: 2.1
Name: py-bbclib
Version: 1.6.1
Summary: The library of BBc-1 transaction data structure definition
Home-page: https://github.com/beyond-blockchain/py-bbclib
Author: beyond-blockchain.org
Author-email: bbc1-dev@beyond-blockchain.org
License: Apache License 2.0
Platform: UNKNOWN
Classifier: Development Status :: 4 - Beta
Classifier: Programming Language :: Python :: 3.5
Classifier: Programming Language :: Python :: 3.6
Classifier: Programming Language :: Python :: 3.7
Classifier: Topic :: Software Development
Requires-Dist: pyOpenSSL (>=16.2.0)
Requires-Dist: cryptography (>=2.1.4)
Requires-Dist: msgpack-python (>=0.4.8)
Requires-Dist: bson
